{
	"$schema": "https://schemas.wp.org/trunk/theme.json",
	"version": 2,
	"settings": {
		"custom": {
			"wporg/ratings-stars": {
				"color": {
					"fill": "var(--wp--preset--color--pomegrade-1)"
				}
			}
		}
	},
	"styles": {
		"blocks": {
			"core/post-title": {
				"elements": {
					"link": {
						"color": {
							"text": "var(--wp--preset--color--blueberry-1)"
						}
					}
				}
			}
		},
		"elements": {
			"h1": {
				"typography": {
					"fontFamily": "var(--wp--preset--font-family--eb-garamond)",
					"fontSize": "38px",
					"lineHeight": "1.3",
					"fontWeight": "400"
				}
			},
			"h2": {
				"typography": {
					"fontFamily": "var(--wp--preset--font-family--eb-garamond)",
					"fontSize": "32px",
					"lineHeight": "1.3",
					"fontWeight": "400"
				}
			}
		}
	}
}
